Metadata-Version: 1.2
Name: comagic-data-api-sdk
Version: 0.0.3
Summary: Comagic data api sdk
Home-page: https://github.com/bzdvdn/comagic-sdk
Author: bzdvdn
Author-email: bzdv.dn@gmail.com
License: MIT
Platform: UNKNOWN
Requires-Python: >=3.6
